{
  "_provenance": {
    "_description": "Input card is transcription-only. Copy user-provided facts faithfully; do not enrich, infer, rewrite into highlights, or add planner-generated peers/sources/topics. Mark every populated field source.",
    "request_language": "",
    "user_provided_paths": [],
    "normalized_metadata_paths": []
  },
  "target_company": "",
  "transaction_type": "",
  "industry": "",
  "subsector": "",
  "geography": "",
  "language": "",
  "deal_context": "",
  "target_business_summary": "",
  "known_investment_highlights": [],
  "known_risks_or_open_questions": [],
  "source_materials": [
    {
      "source_name": "",
      "source_type": "",
      "source_date": "",
      "geography": "",
      "notes": ""
    }
  ],
  "management_hypotheses": [],
  "peer_set": [],
  "must_cover_topics": [],
  "must_avoid_topics": [],
  "research_direction": {
    "_description": "Optional user-provided controls only. Leave empty unless the user explicitly specified preferred websites, domains, source packs, topics, peers, or exclusions. Planner-generated research choices belong in artifacts/research_plan.json.",
    "priority_websites": [],
    "preferred_source_domains": [],
    "preferred_source_packs": [],
    "priority_topics": [],
    "peer_set": [],
    "avoid_topics": [],
    "avoid_sources": []
  }
}
